diject/__init__.py
diject/container.py
diject/exceptions.py
diject/functions.py
diject/injector.py
diject/py.typed
diject/providers/__init__.py
diject/providers/object.py
diject/providers/provider.py
diject/providers/selector.py
diject/providers/collections/__init__.py
diject/providers/collections/dict.py
diject/providers/collections/list.py
diject/providers/collections/tuple.py
diject/providers/creators/__init__.py
diject/providers/creators/creator.py
diject/providers/creators/scoped.py
diject/providers/creators/singleton.py
diject/providers/creators/transient.py
diject/providers/interactions/__init__.py
diject/providers/interactions/attribute.py
diject/providers/interactions/callable.py
diject/providers/interactions/item.py
diject/tools/__init__.py
diject/tools/partial.py
diject/tools/patch.py
diject/utils/__init__.py
diject/utils/cast.py
diject/utils/context.py
diject/utils/lock.py
diject/utils/state.py
diject/utils/status.py
diject/utils/string.py
diject-0.8.0.dist-info/licenses/LICENSE
diject-0.8.0.dist-info/METADATA
diject-0.8.0.dist-info/WHEEL
diject-0.8.0.dist-info/top_level.txt
diject-0.8.0.dist-info/RECORD
